Workbook

Sheet Dashboard
A1: Transport Business Analytics Dashboard | B1: Transport Business Analytics Dashboard | C1: Transport Business Analytics Dashboard | D1: Transport Business Analytics Dashboard | E1: Transport Business Analytics Dashboard | F1: Transport Business Analytics Dashboard | G1: Transport Business Analytics Dashboard | H1: Transport Business Analytics Dashboard | I1: Transport Business Analytics Dashboard | J1: Transport Business Analytics Dashboard | K1: Transport Business Analytics Dashboard | L1: Transport Business Analytics Dashboard | M1: Transport Business Analytics Dashboard | N1: Transport Business Analytics Dashboard | O1: Transport Business Analytics Dashboard | P1: Transport Business Analytics Dashboard
A2: SAMPLE DASHBOARD — replace the Trip Log examples with real trips. Metrics include completed trips from Jan–Jul 2026. | B2: SAMPLE DASHBOARD — replace the Trip Log examples with real trips. Metrics include completed trips from Jan–Jul 2026. | C2: SAMPLE DASHBOARD — replace the Trip Log examples with real trips. Metrics include completed trips from Jan–Jul 2026. | D2: SAMPLE DASHBOARD — replace the Trip Log examples with real trips. Metrics include completed trips from Jan–Jul 2026. | E2: SAMPLE DASHBOARD — replace the Trip Log examples with real trips. Metrics include completed trips from Jan–Jul 2026. | F2: SAMPLE DASHBOARD — replace the Trip Log examples with real trips. Metrics include completed trips from Jan–Jul 2026. | G2: SAMPLE DASHBOARD — replace the Trip Log examples with real trips. Metrics include completed trips from Jan–Jul 2026. | H2: SAMPLE DASHBOARD — replace the Trip Log examples with real trips. Metrics include completed trips from Jan–Jul 2026. | I2: SAMPLE DASHBOARD — replace the Trip Log examples with real trips. Metrics include completed trips from Jan–Jul 2026. | J2: SAMPLE DASHBOARD — replace the Trip Log examples with real trips. Metrics include completed trips from Jan–Jul 2026. | K2: SAMPLE DASHBOARD — replace the Trip Log examples with real trips. Metrics include completed trips from Jan–Jul 2026. | L2: SAMPLE DASHBOARD — replace the Trip Log examples with real trips. Metrics include completed trips from Jan–Jul 2026. | M2: SAMPLE DASHBOARD — replace the Trip Log examples with real trips. Metrics include completed trips from Jan–Jul 2026. | N2: SAMPLE DASHBOARD — replace the Trip Log examples with real trips. Metrics include completed trips from Jan–Jul 2026. | O2: SAMPLE DASHBOARD — replace the Trip Log examples with real trips. Metrics include completed trips from Jan–Jul 2026. | P2: SAMPLE DASHBOARD — replace the Trip Log examples with real trips. Metrics include completed trips from Jan–Jul 2026.
A4: Completed Trips | B4: Completed Trips | C4: Completed Trips | D4: Completed Trips | E4: Revenue | F4: Revenue | G4: Revenue | H4: Revenue | I4: Total Costs | J4: Total Costs | K4: Total Costs | L4: Total Costs | M4: Net Profit | N4: Net Profit | O4: Net Profit | P4: Net Profit
A5: =COUNTIFS('Trip Log'!$A$5:$A$104,"<>",'Trip Log'!$Q$5:$Q$104,"Completed") -> 26 | E5: =SUMIFS('Trip Log'!$H$5:$H$104,'Trip Log'!$Q$5:$Q$104,"Completed") -> 2373000 | I5: =SUMIFS('Trip Log'!$M$5:$M$104,'Trip Log'!$Q$5:$Q$104,"Completed") -> 1295200 | M5: =SUMIFS('Trip Log'!$N$5:$N$104,'Trip Log'!$Q$5:$Q$104,"Completed") -> 1077800
A8: Average Revenue / Trip | B8: Average Revenue / Trip | C8: Average Revenue / Trip | D8: Average Revenue / Trip | E8: Profit Margin | F8: Profit Margin | G8: Profit Margin | H8: Profit Margin | I8: Outstanding Receivables | J8: Outstanding Receivables | K8: Outstanding Receivables | L8: Outstanding Receivables | M8: Average Distance / Trip | N8: Average Distance / Trip | O8: Average Distance / Trip | P8: Average Distance / Trip
A9: =IF(A5=0,0,E5/A5) -> 91269.231 | E9: =IF(E5=0,0,M5/E5) -> 0.454193 | I9: =SUMIFS('Trip Log'!$P$5:$P$104,'Trip Log'!$Q$5:$Q$104,"Completed") -> 218000 | M9: =IF(A5=0,0,SUMIFS('Trip Log'!$G$5:$G$104,'Trip Log'!$Q$5:$Q$104,"Completed")/A5) -> 293.19231
A12: Monthly Performance | B12: Monthly Performance | C12: Monthly Performance | D12: Monthly Performance | E12: Monthly Performance | F12: Monthly Performance
A13: Month | B13: Revenue | C13: Costs | D13: Profit | E13: Completed Trips | F13: Month Start
A14: =TEXT('Setup & Lists'!F5,"mmm yyyy") -> Jan 2026 | B14: =SUMIFS('Trip Log'!$H$5:$H$104,'Trip Log'!$Q$5:$Q$104,"Completed",'Trip Log'!$B$5:$B$104,">="&$F14,'Trip Log'!$B$5:$B$104,"<"&EDATE($F14,1)) -> 205000 | C14: =SUMIFS('Trip Log'!$M$5:$M$104,'Trip Log'!$Q$5:$Q$104,"Completed",'Trip Log'!$B$5:$B$104,">="&$F14,'Trip Log'!$B$5:$B$104,"<"&EDATE($F14,1)) -> 107500 | D14: =SUMIFS('Trip Log'!$N$5:$N$104,'Trip Log'!$Q$5:$Q$104,"Completed",'Trip Log'!$B$5:$B$104,">="&$F14,'Trip Log'!$B$5:$B$104,"<"&EDATE($F14,1)) -> 97500 | E14: =COUNTIFS('Trip Log'!$Q$5:$Q$104,"Completed",'Trip Log'!$B$5:$B$104,">="&$F14,'Trip Log'!$B$5:$B$104,"<"&EDATE($F14,1)) -> 3 | F14: ='Setup & Lists'!F5 -> 46023
A15: =TEXT('Setup & Lists'!F6,"mmm yyyy") -> Feb 2026 | B15: =SUMIFS('Trip Log'!$H$5:$H$104,'Trip Log'!$Q$5:$Q$104,"Completed",'Trip Log'!$B$5:$B$104,">="&$F15,'Trip Log'!$B$5:$B$104,"<"&EDATE($F15,1)) -> 344000 | C15: =SUMIFS('Trip Log'!$M$5:$M$104,'Trip Log'!$Q$5:$Q$104,"Completed",'Trip Log'!$B$5:$B$104,">="&$F15,'Trip Log'!$B$5:$B$104,"<"&EDATE($F15,1)) -> 185600 | D15: =SUMIFS('Trip Log'!$N$5:$N$104,'Trip Log'!$Q$5:$Q$104,"Completed",'Trip Log'!$B$5:$B$104,">="&$F15,'Trip Log'!$B$5:$B$104,"<"&EDATE($F15,1)) -> 158400 | E15: =COUNTIFS('Trip Log'!$Q$5:$Q$104,"Completed",'Trip Log'!$B$5:$B$104,">="&$F15,'Trip Log'!$B$5:$B$104,"<"&EDATE($F15,1)) -> 4 | F15: ='Setup & Lists'!F6 -> 46054
A16: =TEXT('Setup & Lists'!F7,"mmm yyyy") -> Mar 2026 | B16: =SUMIFS('Trip Log'!$H$5:$H$104,'Trip Log'!$Q$5:$Q$104,"Completed",'Trip Log'!$B$5:$B$104,">="&$F16,'Trip Log'!$B$5:$B$104,"<"&EDATE($F16,1)) -> 376000 | C16: =SUMIFS('Trip Log'!$M$5:$M$104,'Trip Log'!$Q$5:$Q$104,"Completed",'Trip Log'!$B$5:$B$104,">="&$F16,'Trip Log'!$B$5:$B$104,"<"&EDATE($F16,1)) -> 208800 | D16: =SUMIFS('Trip Log'!$N$5:$N$104,'Trip Log'!$Q$5:$Q$104,"Completed",'Trip Log'!$B$5:$B$104,">="&$F16,'Trip Log'!$B$5:$B$104,"<"&EDATE($F16,1)) -> 167200 | E16: =COUNTIFS('Trip Log'!$Q$5:$Q$104,"Completed",'Trip Log'!$B$5:$B$104,">="&$F16,'Trip Log'!$B$5:$B$104,"<"&EDATE($F16,1)) -> 4 | F16: ='Setup & Lists'!F7 -> 46082
A17: =TEXT('Setup & Lists'!F8,"mmm yyyy") -> Apr 2026 | B17: =SUMIFS('Trip Log'!$H$5:$H$104,'Trip Log'!$Q$5:$Q$104,"Completed",'Trip Log'!$B$5:$B$104,">="&$F17,'Trip Log'!$B$5:$B$104,"<"&EDATE($F17,1)) -> 397000 | C17: =SUMIFS('Trip Log'!$M$5:$M$104,'Trip Log'!$Q$5:$Q$104,"Completed",'Trip Log'!$B$5:$B$104,">="&$F17,'Trip Log'!$B$5:$B$104,"<"&EDATE($F17,1)) -> 219000 | D17: =SUMIFS('Trip Log'!$N$5:$N$104,'Trip Log'!$Q$5:$Q$104,"Completed",'Trip Log'!$B$5:$B$104,">="&$F17,'Trip Log'!$B$5:$B$104,"<"&EDATE($F17,1)) -> 178000 | E17: =COUNTIFS('Trip Log'!$Q$5:$Q$104,"Completed",'Trip Log'!$B$5:$B$104,">="&$F17,'Trip Log'!$B$5:$B$104,"<"&EDATE($F17,1)) -> 4 | F17: ='Setup & Lists'!F8 -> 46113
A18: =TEXT('Setup & Lists'!F9,"mmm yyyy") -> May 2026 | B18: =SUMIFS('Trip Log'!$H$5:$H$104,'Trip Log'!$Q$5:$Q$104,"Completed",'Trip Log'!$B$5:$B$104,">="&$F18,'Trip Log'!$B$5:$B$104,"<"&EDATE($F18,1)) -> 255000 | C18: =SUMIFS('Trip Log'!$M$5:$M$104,'Trip Log'!$Q$5:$Q$104,"Completed",'Trip Log'!$B$5:$B$104,">="&$F18,'Trip Log'!$B$5:$B$104,"<"&EDATE($F18,1)) -> 133600 | D18: =SUMIFS('Trip Log'!$N$5:$N$104,'Trip Log'!$Q$5:$Q$104,"Completed",'Trip Log'!$B$5:$B$104,">="&$F18,'Trip Log'!$B$5:$B$104,"<"&EDATE($F18,1)) -> 121400 | E18: =COUNTIFS('Trip Log'!$Q$5:$Q$104,"Completed",'Trip Log'!$B$5:$B$104,">="&$F18,'Trip Log'!$B$5:$B$104,"<"&EDATE($F18,1)) -> 3 | F18: ='Setup & Lists'!F9 -> 46143
A19: =TEXT('Setup & Lists'!F10,"mmm yyyy") -> Jun 2026 | B19: =SUMIFS('Trip Log'!$H$5:$H$104,'Trip Log'!$Q$5:$Q$104,"Completed",'Trip Log'!$B$5:$B$104,">="&$F19,'Trip Log'!$B$5:$B$104,"<"&EDATE($F19,1)) -> 396000 | C19: =SUMIFS('Trip Log'!$M$5:$M$104,'Trip Log'!$Q$5:$Q$104,"Completed",'Trip Log'!$B$5:$B$104,">="&$F19,'Trip Log'!$B$5:$B$104,"<"&EDATE($F19,1)) -> 221900 | D19: =SUMIFS('Trip Log'!$N$5:$N$104,'Trip Log'!$Q$5:$Q$104,"Completed",'Trip Log'!$B$5:$B$104,">="&$F19,'Trip Log'!$B$5:$B$104,"<"&EDATE($F19,1)) -> 174100 | E19: =COUNTIFS('Trip Log'!$Q$5:$Q$104,"Completed",'Trip Log'!$B$5:$B$104,">="&$F19,'Trip Log'!$B$5:$B$104,"<"&EDATE($F19,1)) -> 4 | F19: ='Setup & Lists'!F10 -> 46174
A20: =TEXT('Setup & Lists'!F11,"mmm yyyy") -> Jul 2026 | B20: =SUMIFS('Trip Log'!$H$5:$H$104,'Trip Log'!$Q$5:$Q$104,"Completed",'Trip Log'!$B$5:$B$104,">="&$F20,'Trip Log'!$B$5:$B$104,"<"&EDATE($F20,1)) -> 400000 | C20: =SUMIFS('Trip Log'!$M$5:$M$104,'Trip Log'!$Q$5:$Q$104,"Completed",'Trip Log'!$B$5:$B$104,">="&$F20,'Trip Log'!$B$5:$B$104,"<"&EDATE($F20,1)) -> 218800 | D20: =SUMIFS('Trip Log'!$N$5:$N$104,'Trip Log'!$Q$5:$Q$104,"Completed",'Trip Log'!$B$5:$B$104,">="&$F20,'Trip Log'!$B$5:$B$104,"<"&EDATE($F20,1)) -> 181200 | E20: =COUNTIFS('Trip Log'!$Q$5:$Q$104,"Completed",'Trip Log'!$B$5:$B$104,">="&$F20,'Trip Log'!$B$5:$B$104,"<"&EDATE($F20,1)) -> 4 | F20: ='Setup & Lists'!F11 -> 46204
A23: Lead Source Performance | B23: Lead Source Performance | C23: Lead Source Performance | D23: Lead Source Performance
A24: Lead Source | B24: Completed Trips | C24: Revenue | D24: Profit
A25: ='Setup & Lists'!A5 -> Facebook | B25: =COUNTIFS('Trip Log'!$Q$5:$Q$104,"Completed",'Trip Log'!$S$5:$S$104,$A25) -> 6 | C25: =SUMIFS('Trip Log'!$H$5:$H$104,'Trip Log'!$Q$5:$Q$104,"Completed",'Trip Log'!$S$5:$S$104,$A25) -> 376000 | D25: =SUMIFS('Trip Log'!$N$5:$N$104,'Trip Log'!$Q$5:$Q$104,"Completed",'Trip Log'!$S$5:$S$104,$A25) -> 146600
A26: ='Setup & Lists'!A6 -> Referral | B26: =COUNTIFS('Trip Log'!$Q$5:$Q$104,"Completed",'Trip Log'!$S$5:$S$104,$A26) -> 5 | C26: =SUMIFS('Trip Log'!$H$5:$H$104,'Trip Log'!$Q$5:$Q$104,"Completed",'Trip Log'!$S$5:$S$104,$A26) -> 435000 | D26: =SUMIFS('Trip Log'!$N$5:$N$104,'Trip Log'!$Q$5:$Q$104,"Completed",'Trip Log'!$S$5:$S$104,$A26) -> 186700
A27: ='Setup & Lists'!A7 -> Adda/Network | B27: =COUNTIFS('Trip Log'!$Q$5:$Q$104,"Completed",'Trip Log'!$S$5:$S$104,$A27) -> 5 | C27: =SUMIFS('Trip Log'!$H$5:$H$104,'Trip Log'!$Q$5:$Q$104,"Completed",'Trip Log'!$S$5:$S$104,$A27) -> 505000 | D27: =SUMIFS('Trip Log'!$N$5:$N$104,'Trip Log'!$Q$5:$Q$104,"Completed",'Trip Log'!$S$5:$S$104,$A27) -> 239600
A28: ='Setup & Lists'!A8 -> Repeat Customer | B28: =COUNTIFS('Trip Log'!$Q$5:$Q$104,"Completed",'Trip Log'!$S$5:$S$104,$A28) -> 6 | C28: =SUMIFS('Trip Log'!$H$5:$H$104,'Trip Log'!$Q$5:$Q$104,"Completed",'Trip Log'!$S$5:$S$104,$A28) -> 655000 | D28: =SUMIFS('Trip Log'!$N$5:$N$104,'Trip Log'!$Q$5:$Q$104,"Completed",'Trip Log'!$S$5:$S$104,$A28) -> 314700
A29: ='Setup & Lists'!A9 -> WhatsApp | B29: =COUNTIFS('Trip Log'!$Q$5:$Q$104,"Completed",'Trip Log'!$S$5:$S$104,$A29) -> 4 | C29: =SUMIFS('Trip Log'!$H$5:$H$104,'Trip Log'!$Q$5:$Q$104,"Completed",'Trip Log'!$S$5:$S$104,$A29) -> 402000 | D29: =SUMIFS('Trip Log'!$N$5:$N$104,'Trip Log'!$Q$5:$Q$104,"Completed",'Trip Log'!$S$5:$S$104,$A29) -> 190200
A32: Service Type Performance | B32: Service Type Performance | C32: Service Type Performance | D32: Service Type Performance | E32: Service Type Performance
A33: Service Type | B33: Trips | C33: Revenue | D33: Profit | E33: Profit Margin
A34: ='Setup & Lists'!B5 -> Agricultural Goods | B34: =COUNTIFS('Trip Log'!$Q$5:$Q$104,"Completed",'Trip Log'!$C$5:$C$104,$A34) -> 8 | C34: =SUMIFS('Trip Log'!$H$5:$H$104,'Trip Log'!$Q$5:$Q$104,"Completed",'Trip Log'!$C$5:$C$104,$A34) -> 886000 | D34: =SUMIFS('Trip Log'!$N$5:$N$104,'Trip Log'!$Q$5:$Q$104,"Completed",'Trip Log'!$C$5:$C$104,$A34) -> 426500 | E34: =IF(C34=0,0,D34/C34) -> 0.48137698
A35: ='Setup & Lists'!B6 -> General Goods | B35: =COUNTIFS('Trip Log'!$Q$5:$Q$104,"Completed",'Trip Log'!$C$5:$C$104,$A35) -> 11 | C35: =SUMIFS('Trip Log'!$H$5:$H$104,'Trip Log'!$Q$5:$Q$104,"Completed",'Trip Log'!$C$5:$C$104,$A35) -> 1099000 | D35: =SUMIFS('Trip Log'!$N$5:$N$104,'Trip Log'!$Q$5:$Q$104,"Completed",'Trip Log'!$C$5:$C$104,$A35) -> 523400 | E35: =IF(C35=0,0,D35/C35) -> 0.47625114
A36: ='Setup & Lists'!B7 -> Home Shifting | B36: =COUNTIFS('Trip Log'!$Q$5:$Q$104,"Completed",'Trip Log'!$C$5:$C$104,$A36) -> 7 | C36: =SUMIFS('Trip Log'!$H$5:$H$104,'Trip Log'!$Q$5:$Q$104,"Completed",'Trip Log'!$C$5:$C$104,$A36) -> 388000 | D36: =SUMIFS('Trip Log'!$N$5:$N$104,'Trip Log'!$Q$5:$Q$104,"Completed",'Trip Log'!$C$5:$C$104,$A36) -> 127900 | E36: =IF(C36=0,0,D36/C36) -> 0.32963918
A39: Yearly Performance
A40: Year | B40: Completed Trips | C40: Revenue | D40: Total Costs | E40: Net Profit | F40: Profit Margin
A41: =IF(COUNTA('Trip Log'!$B$5:$B$104)=0,"",YEAR(MAX('Trip Log'!$B$5:$B$104))) -> 2026 | B41: =IF($A41="",0,COUNTIFS('Trip Log'!$Q$5:$Q$104,"Completed",'Trip Log'!$B$5:$B$104,">="&DATE($A41,1,1),'Trip Log'!$B$5:$B$104,"<"&DATE($A41+1,1,1))) -> 26 | C41: =IF($A41="",0,SUMIFS('Trip Log'!$H$5:$H$104,'Trip Log'!$Q$5:$Q$104,"Completed",'Trip Log'!$B$5:$B$104,">="&DATE($A41,1,1),'Trip Log'!$B$5:$B$104,"<"&DATE($A41+1,1,1))) -> 2373000 | D41: =IF($A41="",0,SUMIFS('Trip Log'!$M$5:$M$104,'Trip Log'!$Q$5:$Q$104,"Completed",'Trip Log'!$B$5:$B$104,">="&DATE($A41,1,1),'Trip Log'!$B$5:$B$104,"<"&DATE($A41+1,1,1))) -> 1295200 | E41: =IF($A41="",0,SUMIFS('Trip Log'!$N$5:$N$104,'Trip Log'!$Q$5:$Q$104,"Completed",'Trip Log'!$B$5:$B$104,">="&DATE($A41,1,1),'Trip Log'!$B$5:$B$104,"<"&DATE($A41+1,1,1))) -> 1077800 | F41: =IF(C41=0,0,E41/C41) -> 0.454193
A42: Latest year in the Trip Log • Completed trips only
A45: What to Do Next
A46: 1. Follow up on outstanding customer payments. 2. Compare lead sources and focus marketing on sources producing profitable trips. 3. Replace sample data with actual trips each week.

Sheet Trip Log
A1: Transport Business Trip Log | B1: Transport Business Trip Log | C1: Transport Business Trip Log | D1: Transport Business Trip Log | E1: Transport Business Trip Log | F1: Transport Business Trip Log | G1: Transport Business Trip Log | H1: Transport Business Trip Log | I1: Transport Business Trip Log | J1: Transport Business Trip Log | K1: Transport Business Trip Log | L1: Transport Business Trip Log | M1: Transport Business Trip Log | N1: Transport Business Trip Log | O1: Transport Business Trip Log | P1: Transport Business Trip Log | Q1: Transport Business Trip Log | R1: Transport Business Trip Log | S1: Transport Business Trip Log | T1: Transport Business Trip Log | U1: Transport Business Trip Log
A2: SAMPLE DATA — replace the example trips with your actual records. All amounts are in Pakistani Rupees (PKR). | B2: SAMPLE DATA — replace the example trips with your actual records. All amounts are in Pakistani Rupees (PKR). | C2: SAMPLE DATA — replace the example trips with your actual records. All amounts are in Pakistani Rupees (PKR). | D2: SAMPLE DATA — replace the example trips with your actual records. All amounts are in Pakistani Rupees (PKR). | E2: SAMPLE DATA — replace the example trips with your actual records. All amounts are in Pakistani Rupees (PKR). | F2: SAMPLE DATA — replace the example trips with your actual records. All amounts are in Pakistani Rupees (PKR). | G2: SAMPLE DATA — replace the example trips with your actual records. All amounts are in Pakistani Rupees (PKR). | H2: SAMPLE DATA — replace the example trips with your actual records. All amounts are in Pakistani Rupees (PKR). | I2: SAMPLE DATA — replace the example trips with your actual records. All amounts are in Pakistani Rupees (PKR). | J2: SAMPLE DATA — replace the example trips with your actual records. All amounts are in Pakistani Rupees (PKR). | K2: SAMPLE DATA — replace the example trips with your actual records. All amounts are in Pakistani Rupees (PKR). | L2: SAMPLE DATA — replace the example trips with your actual records. All amounts are in Pakistani Rupees (PKR). | M2: SAMPLE DATA — replace the example trips with your actual records. All amounts are in Pakistani Rupees (PKR). | N2: SAMPLE DATA — replace the example trips with your actual records. All amounts are in Pakistani Rupees (PKR). | O2: SAMPLE DATA — replace the example trips with your actual records. All amounts are in Pakistani Rupees (PKR). | P2: SAMPLE DATA — replace the example trips with your actual records. All amounts are in Pakistani Rupees (PKR). | Q2: SAMPLE DATA — replace the example trips with your actual records. All amounts are in Pakistani Rupees (PKR). | R2: SAMPLE DATA — replace the example trips with your actual records. All amounts are in Pakistani Rupees (PKR). | S2: SAMPLE DATA — replace the example trips with your actual records. All amounts are in Pakistani Rupees (PKR). | T2: SAMPLE DATA — replace the example trips with your actual records. All amounts are in Pakistani Rupees (PKR). | U2: SAMPLE DATA — replace the example trips with your actual records. All amounts are in Pakistani Rupees (PKR).
A3: Enter data in the white columns. Total Cost, Profit, Outstanding, and Payment Status calculate automatically. | B3: Enter data in the white columns. Total Cost, Profit, Outstanding, and Payment Status calculate automatically. | C3: Enter data in the white columns. Total Cost, Profit, Outstanding, and Payment Status calculate automatically. | D3: Enter data in the white columns. Total Cost, Profit, Outstanding, and Payment Status calculate automatically. | E3: Enter data in the white columns. Total Cost, Profit, Outstanding, and Payment Status calculate automatically. | F3: Enter data in the white columns. Total Cost, Profit, Outstanding, and Payment Status calculate automatically. | G3: Enter data in the white columns. Total Cost, Profit, Outstanding, and Payment Status calculate automatically. | H3: Enter data in the white columns. Total Cost, Profit, Outstanding, and Payment Status calculate automatically. | I3: Enter data in the white columns. Total Cost, Profit, Outstanding, and Payment Status calculate automatically. | J3: Enter data in the white columns. Total Cost, Profit, Outstanding, and Payment Status calculate automatically. | K3: Enter data in the white columns. Total Cost, Profit, Outstanding, and Payment Status calculate automatically. | L3: Enter data in the white columns. Total Cost, Profit, Outstanding, and Payment Status calculate automatically. | M3: Enter data in the white columns. Total Cost, Profit, Outstanding, and Payment Status calculate automatically. | N3: Enter data in the white columns. Total Cost, Profit, Outstanding, and Payment Status calculate automatically. | O3: Enter data in the white columns. Total Cost, Profit, Outstanding, and Payment Status calculate automatically. | P3: Enter data in the white columns. Total Cost, Profit, Outstanding, and Payment Status calculate automatically. | Q3: Enter data in the white columns. Total Cost, Profit, Outstanding, and Payment Status calculate automatically. | R3: Enter data in the white columns. Total Cost, Profit, Outstanding, and Payment Status calculate automatically. | S3: Enter data in the white columns. Total Cost, Profit, Outstanding, and Payment Status calculate automatically. | T3: Enter data in the white columns. Total Cost, Profit, Outstanding, and Payment Status calculate automatically. | U3: Enter data in the white columns. Total Cost, Profit, Outstanding, and Payment Status calculate automatically.
A4: Trip ID | B4: Date | C4: Service Type | D4: Cargo Type | E4: Origin | F4: Destination | G4: Distance (km) | H4: Revenue (PKR) | I4: Fuel Cost | J4: Driver/Labor | K4: Tolls | L4: Other Cost | M4: Total Cost | N4: Profit | O4: Amount Received | P4: Outstanding | Q4: Trip Status | R4: Payment Status | S4: Lead Source | T4: Customer Type | U4: Notes
A5: TB-001 | B5: 46027 | C5: Agricultural Goods | D5: Sugarcane | E5: Mianwali | F5: Faisalabad | G5: 290 | H5: 95000 | I5: 33000 | J5: 9000 | K5: 4500 | L5: 2500 | M5: =IF($A5="","",SUM($I5:$L5)) -> 49000 | N5: =IF($A5="","",$H5-$M5) -> 46000 | O5: 95000 | P5: =IF($A5="","",MAX(0,$H5-$O5)) -> 0 | Q5: Completed | R5: =IF($A5="","",IF($H5=0,"No Revenue",IF($O5>=$H5,"Paid",IF($O5>0,"Partial","Unpaid")))) -> Paid | S5: Referral | T5: Trader | U5: Sugarcane load
A6: TB-002 | B6: 46036 | C6: General Goods | D6: Fertilizer | E6: Rawalpindi | F6: Mianwali | G6: 250 | H6: 82000 | I6: 30000 | J6: 8000 | K6: 3500 | L6: 1500 | M6: =IF($A6="","",SUM($I6:$L6)) -> 43000 | N6: =IF($A6="","",$H6-$M6) -> 39000 | O6: 60000 | P6: =IF($A6="","",MAX(0,$H6-$O6)) -> 22000 | Q6: Completed | R6: =IF($A6="","",IF($H6=0,"No Revenue",IF($O6>=$H6,"Paid",IF($O6>0,"Partial","Unpaid")))) -> Partial | S6: Adda/Network | T6: Business | U6: Balance due
A7: TB-003 | B7: 46045 | C7: Home Shifting | D7: Household Items | E7: Islamabad | F7: Rawalpindi | G7: 35 | H7: 28000 | I7: 5000 | J7: 9000 | K7: 500 | L7: 1000 | M7: =IF($A7="","",SUM($I7:$L7)) -> 15500 | N7: =IF($A7="","",$H7-$M7) -> 12500 | O7: 28000 | P7: =IF($A7="","",MAX(0,$H7-$O7)) -> 0 | Q7: Completed | R7: =IF($A7="","",IF($H7=0,"No Revenue",IF($O7>=$H7,"Paid",IF($O7>0,"Partial","Unpaid")))) -> Paid | S7: Facebook | T7: Household | U7: Local shifting
A8: TB-004 | B8: 46055 | C8: Agricultural Goods | D8: Rice | E8: Mianwali | F8: Lahore | G8: 420 | H8: 125000 | I8: 47000 | J8: 12000 | K8: 6500 | L8: 2500 | M8: =IF($A8="","",SUM($I8:$L8)) -> 68000 | N8: =IF($A8="","",$H8-$M8) -> 57000 | O8: 125000 | P8: =IF($A8="","",MAX(0,$H8-$O8)) -> 0 | Q8: Completed | R8: =IF($A8="","",IF($H8=0,"No Revenue",IF($O8>=$H8,"Paid",IF($O8>0,"Partial","Unpaid")))) -> Paid | S8: Repeat Customer | T8: Trader | U8: Rice bags
A9: TB-005 | B9: 46064 | C9: General Goods | D9: Cement | E9: Chakwal | F9: Mianwali | G9: 240 | H9: 78000 | I9: 29000 | J9: 8500 | K9: 3000 | L9: 1800 | M9: =IF($A9="","",SUM($I9:$L9)) -> 42300 | N9: =IF($A9="","",$H9-$M9) -> 35700 | O9: 78000 | P9: =IF($A9="","",MAX(0,$H9-$O9)) -> 0 | Q9: Completed | R9: =IF($A9="","",IF($H9=0,"No Revenue",IF($O9>=$H9,"Paid",IF($O9>0,"Partial","Unpaid")))) -> Paid | S9: WhatsApp | T9: Business | U9: Cement delivery
A10: TB-006 | B10: 46073 | C10: Home Shifting | D10: Household Items | E10: Rawalpindi | F10: Islamabad | G10: 28 | H10: 26000 | I10: 4500 | J10: 9000 | K10: 400 | L10: 1200 | M10: =IF($A10="","",SUM($I10:$L10)) -> 15100 | N10: =IF($A10="","",$H10-$M10) -> 10900 | O10: 20000 | P10: =IF($A10="","",MAX(0,$H10-$O10)) -> 6000 | Q10: Completed | R10: =IF($A10="","",IF($H10=0,"No Revenue",IF($O10>=$H10,"Paid",IF($O10>0,"Partial","Unpaid")))) -> Partial | S10: Facebook | T10: Household | U10: Partial payment
A11: TB-007 | B11: 46080 | C11: General Goods | D11: Furniture | E11: Lahore | F11: Rawalpindi | G11: 375 | H11: 115000 | I11: 41000 | J11: 11500 | K11: 5500 | L11: 2200 | M11: =IF($A11="","",SUM($I11:$L11)) -> 60200 | N11: =IF($A11="","",$H11-$M11) -> 54800 | O11: 115000 | P11: =IF($A11="","",MAX(0,$H11-$O11)) -> 0 | Q11: Completed | R11: =IF($A11="","",IF($H11=0,"No Revenue",IF($O11>=$H11,"Paid",IF($O11>0,"Partial","Unpaid")))) -> Paid | S11: Repeat Customer | T11: Business | U11: Furniture delivery
A12: TB-008 | B12: 46085 | C12: Agricultural Goods | D12: Wheat | E12: Mianwali | F12: Multan | G12: 370 | H12: 112000 | I12: 40000 | J12: 11000 | K12: 5000 | L12: 2000 | M12: =IF($A12="","",SUM($I12:$L12)) -> 58000 | N12: =IF($A12="","",$H12-$M12) -> 54000 | O12: 112000 | P12: =IF($A12="","",MAX(0,$H12-$O12)) -> 0 | Q12: Completed | R12: =IF($A12="","",IF($H12=0,"No Revenue",IF($O12>=$H12,"Paid",IF($O12>0,"Partial","Unpaid")))) -> Paid | S12: Referral | T12: Trader | U12: Wheat load
A13: TB-009 | B13: 46093 | C13: General Goods | D13: Construction Materials | E13: Islamabad | F13: Mianwali | G13: 240 | H13: 79000 | I13: 29000 | J13: 8500 | K13: 3500 | L13: 1500 | M13: =IF($A13="","",SUM($I13:$L13)) -> 42500 | N13: =IF($A13="","",$H13-$M13) -> 36500 | O13: 79000 | P13: =IF($A13="","",MAX(0,$H13-$O13)) -> 0 | Q13: Completed | R13: =IF($A13="","",IF($H13=0,"No Revenue",IF($O13>=$H13,"Paid",IF($O13>0,"Partial","Unpaid")))) -> Paid | S13: Adda/Network | T13: Business | U13: Building materials
A14: TB-010 | B14: 46101 | C14: Home Shifting | D14: Household Items | E14: Rawalpindi | F14: Lahore | G14: 375 | H14: 88000 | I14: 38000 | J14: 15000 | K14: 5000 | L14: 2000 | M14: =IF($A14="","",SUM($I14:$L14)) -> 60000 | N14: =IF($A14="","",$H14-$M14) -> 28000 | O14: 70000 | P14: =IF($A14="","",MAX(0,$H14-$O14)) -> 18000 | Q14: Completed | R14: =IF($A14="","",IF($H14=0,"No Revenue",IF($O14>=$H14,"Paid",IF($O14>0,"Partial","Unpaid")))) -> Partial | S14: Facebook | T14: Household | U14: Intercity shifting
A15: TB-011 | B15: 46109 | C15: Agricultural Goods | D15: Rice | E15: Mianwali | F15: Faisalabad | G15: 290 | H15: 97000 | I15: 33000 | J15: 9000 | K15: 4500 | L15: 1800 | M15: =IF($A15="","",SUM($I15:$L15)) -> 48300 | N15: =IF($A15="","",$H15-$M15) -> 48700 | O15: 97000 | P15: =IF($A15="","",MAX(0,$H15-$O15)) -> 0 | Q15: Completed | R15: =IF($A15="","",IF($H15=0,"No Revenue",IF($O15>=$H15,"Paid",IF($O15>0,"Partial","Unpaid")))) -> Paid | S15: Repeat Customer | T15: Trader | U15: Rice load
A16: TB-012 | B16: 46118 | C16: General Goods | D16: Packaging Material | E16: Faisalabad | F16: Rawalpindi | G16: 320 | H16: 101000 | I16: 36000 | J16: 10000 | K16: 4500 | L16: 2000 | M16: =IF($A16="","",SUM($I16:$L16)) -> 52500 | N16: =IF($A16="","",$H16-$M16) -> 48500 | O16: 101000 | P16: =IF($A16="","",MAX(0,$H16-$O16)) -> 0 | Q16: Completed | R16: =IF($A16="","",IF($H16=0,"No Revenue",IF($O16>=$H16,"Paid",IF($O16>0,"Partial","Unpaid")))) -> Paid | S16: WhatsApp | T16: Business | U16: Packaging delivery
... A33: TB-029 | B33: 46234 | C33: General Goods | D33: Cement | E33: Mianwali | F33: Rawalpindi | G33: 250 | H33: 0 | I33: 0 | J33: 0 | K33: 0 | L33: 2000 | M33: =IF($A33="","",SUM($I33:$L33)) -> 2000 | N33: =IF($A33="","",$H33-$M33) -> -2000 | O33: 0 | P33: =IF($A33="","",MAX(0,$H33-$O33)) -> 0 | Q33: Cancelled | R33: =IF($A33="","",IF($H33=0,"No Revenue",IF($O33>=$H33,"Paid",IF($O33>0,"Partial","Unpaid")))) -> No Revenue | S33: Facebook | T33: Business | U33: Booking cancelled
M34: =IF($A34="","",SUM($I34:$L34)) | N34: =IF($A34="","",$H34-$M34) | P34: =IF($A34="","",MAX(0,$H34-$O34)) | R34: =IF($A34="","",IF($H34=0,"No Revenue",IF($O34>=$H34,"Paid",IF($O34>0,"Partial","Unpaid"))))
M35: =IF($A35="","",SUM($I35:$L35)) | N35: =IF($A35="","",$H35-$M35) | P35: =IF($A35="","",MAX(0,$H35-$O35)) | R35: =IF($A35="","",IF($H35=0,"No Revenue",IF($O35>=$H35,"Paid",IF($O35>0,"Partial","Unpaid"))))
M36: =IF($A36="","",SUM($I36:$L36)) | N36: =IF($A36="","",$H36-$M36) | P36: =IF($A36="","",MAX(0,$H36-$O36)) | R36: =IF($A36="","",IF($H36=0,"No Revenue",IF($O36>=$H36,"Paid",IF($O36>0,"Partial","Unpaid"))))
M37: =IF($A37="","",SUM($I37:$L37)) | N37: =IF($A37="","",$H37-$M37) | P37: =IF($A37="","",MAX(0,$H37-$O37)) | R37: =IF($A37="","",IF($H37=0,"No Revenue",IF($O37>=$H37,"Paid",IF($O37>0,"Partial","Unpaid"))))
M38: =IF($A38="","",SUM($I38:$L38)) | N38: =IF($A38="","",$H38-$M38) | P38: =IF($A38="","",MAX(0,$H38-$O38)) | R38: =IF($A38="","",IF($H38=0,"No Revenue",IF($O38>=$H38,"Paid",IF($O38>0,"Partial","Unpaid"))))
M39: =IF($A39="","",SUM($I39:$L39)) | N39: =IF($A39="","",$H39-$M39) | P39: =IF($A39="","",MAX(0,$H39-$O39)) | R39: =IF($A39="","",IF($H39=0,"No Revenue",IF($O39>=$H39,"Paid",IF($O39>0,"Partial","Unpaid"))))
M40: =IF($A40="","",SUM($I40:$L40)) | N40: =IF($A40="","",$H40-$M40) | P40: =IF($A40="","",MAX(0,$H40-$O40)) | R40: =IF($A40="","",IF($H40=0,"No Revenue",IF($O40>=$H40,"Paid",IF($O40>0,"Partial","Unpaid"))))
M41: =IF($A41="","",SUM($I41:$L41)) | N41: =IF($A41="","",$H41-$M41) | P41: =IF($A41="","",MAX(0,$H41-$O41)) | R41: =IF($A41="","",IF($H41=0,"No Revenue",IF($O41>=$H41,"Paid",IF($O41>0,"Partial","Unpaid"))))
M42: =IF($A42="","",SUM($I42:$L42)) | N42: =IF($A42="","",$H42-$M42) | P42: =IF($A42="","",MAX(0,$H42-$O42)) | R42: =IF($A42="","",IF($H42=0,"No Revenue",IF($O42>=$H42,"Paid",IF($O42>0,"Partial","Unpaid"))))
M43: =IF($A43="","",SUM($I43:$L43)) | N43: =IF($A43="","",$H43-$M43) | P43: =IF($A43="","",MAX(0,$H43-$O43)) | R43: =IF($A43="","",IF($H43=0,"No Revenue",IF($O43>=$H43,"Paid",IF($O43>0,"Partial","Unpaid"))))
M44: =IF($A44="","",SUM($I44:$L44)) | N44: =IF($A44="","",$H44-$M44) | P44: =IF($A44="","",MAX(0,$H44-$O44)) | R44: =IF($A44="","",IF($H44=0,"No Revenue",IF($O44>=$H44,"Paid",IF($O44>0,"Partial","Unpaid"))))
M45: =IF($A45="","",SUM($I45:$L45)) | N45: =IF($A45="","",$H45-$M45) | P45: =IF($A45="","",MAX(0,$H45-$O45)) | R45: =IF($A45="","",IF($H45=0,"No Revenue",IF($O45>=$H45,"Paid",IF($O45>0,"Partial","Unpaid"))))
... M104: =IF($A104="","",SUM($I104:$L104)) | N104: =IF($A104="","",$H104-$M104) | P104: =IF($A104="","",MAX(0,$H104-$O104)) | R104: =IF($A104="","",IF($H104=0,"No Revenue",IF($O104>=$H104,"Paid",IF($O104>0,"Partial","Unpaid"))))

Sheet Setup & Lists
A1: Transport Business Setup & Lists | B1: Transport Business Setup & Lists | C1: Transport Business Setup & Lists | D1: Transport Business Setup & Lists | E1: Transport Business Setup & Lists | F1: Transport Business Setup & Lists
A2: Edit these lists to match your business. The Trip Log dropdowns and Dashboard summaries use these categories. | B2: Edit these lists to match your business. The Trip Log dropdowns and Dashboard summaries use these categories. | C2: Edit these lists to match your business. The Trip Log dropdowns and Dashboard summaries use these categories. | D2: Edit these lists to match your business. The Trip Log dropdowns and Dashboard summaries use these categories. | E2: Edit these lists to match your business. The Trip Log dropdowns and Dashboard summaries use these categories. | F2: Edit these lists to match your business. The Trip Log dropdowns and Dashboard summaries use these categories.
A4: Lead Sources | B4: Service Types | C4: Cargo Types | D4: Trip Status | E4: Customer Types | F4: Month Start
A5: Facebook | B5: Agricultural Goods | C5: Sugarcane | D5: Completed | E5: Trader | F5: 46023
A6: Referral | B6: General Goods | C6: Rice | D6: Scheduled | E6: Business | F6: 46054
A7: Adda/Network | B7: Home Shifting | C7: Wheat | D7: Cancelled | E7: Household | F7: 46082
A8: Repeat Customer | C8: Fertilizer | F8: 46113
A9: WhatsApp | C9: Cement | F9: 46143
C10: Furniture | F10: 46174
C11: Construction Materials | F11: 46204
C12: Packaging Material
C13: Household Items
A16: How to use this workbook | B16: How to use this workbook | C16: How to use this workbook | D16: How to use this workbook | E16: How to use this workbook | F16: How to use this workbook
A17: 1 | B17: Open Trip Log | C17: Replace the sample rows with your actual trips.
A18: 2 | B18: Enter trip details | C18: Fill the white input columns; grey columns calculate automatically.
A19: 3 | B19: Use dropdowns | C19: Select service type, status, lead source, and customer type.
A20: 4 | B20: Check Dashboard | C20: Review KPIs plus monthly, yearly, lead-source, and service-type performance.
A21: 5 | B21: Add more rows | C21: Use the reserved rows through row 104 for future trips.
